{
	"animations": [
		{
			"loop": false,
			"offsets": [
				0,
				0
			],
			"anim": "idle",
			"fps": 31,
			"name": "bambi idle",
			"indices": []
		},
		{
			"loop": false,
			"offsets": [
				70,
				0
			],
			"anim": "singLEFT",
			"fps": 32,
			"name": "bambi left",
			"indices": []
		},
		{
			"loop": false,
			"offsets": [
				-10,
				0
			],
			"anim": "singRIGHT",
			"fps": 32,
			"name": "bambi right",
			"indices": []
		},
		{
			"loop": false,
			"offsets": [
				60,
				30
			],
			"anim": "singUP",
			"fps": 32,
			"name": "bambi up",
			"indices": []
		},
		{
			"loop": false,
			"offsets": [
				20,
				-40
			],
			"anim": "singDOWN",
			"fps": 32,
			"name": "bambi down",
			"indices": []
		}
	],
	"no_antialiasing": false,
	"image": "characters/bambi",
	"position": [
		240,
		410
	],
	"healthicon": "bambi",
	"flip_x": false,
	"healthbar_colors": [
		12,
		181,
		0
	],
	"camera_position": [
		0,
		0
	],
	"sing_duration": 6.1,
	"scale": 1.1
}